setup.cfg
setup.py
pyramda/__init__.py
pyramda/getattr.py
pyramda/getattr_test.py
pyramda/isinstance.py
pyramda/isinstance_test.py
pyramda.egg-info/PKG-INFO
pyramda.egg-info/SOURCES.txt
pyramda.egg-info/dependency_links.txt
pyramda.egg-info/not-zip-safe
pyramda.egg-info/requires.txt
pyramda.egg-info/top_level.txt
pyramda/dictionary/__init__.py
pyramda/dictionary/getitem.py
pyramda/dictionary/getitem_test.py
pyramda/dictionary/item_path.py
pyramda/dictionary/item_path_test.py
pyramda/dictionary/keys.py
pyramda/dictionary/keys_test.py
pyramda/dictionary/map_dict.py
pyramda/dictionary/map_dict_test.py
pyramda/dictionary/pick.py
pyramda/dictionary/pick_test.py
pyramda/dictionary/values.py
pyramda/dictionary/values_test.py
pyramda/function/__init__.py
pyramda/function/always.py
pyramda/function/always_test.py
pyramda/function/apply.py
pyramda/function/apply_test.py
pyramda/function/compose.py
pyramda/function/compose_test.py
pyramda/function/curry.py
pyramda/function/curry_test.py
pyramda/function/identity.py
pyramda/function/identity_test.py
pyramda/function/tap.py
pyramda/function/tap_test.py
pyramda/iterable/__init__.py
pyramda/iterable/all_satisfy.py
pyramda/iterable/all_satisfy_test.py
pyramda/iterable/any_satisfy.py
pyramda/iterable/any_satisfy_test.py
pyramda/iterable/chain.py
pyramda/iterable/chain_test.py
pyramda/iterable/concat.py
pyramda/iterable/concat_test.py
pyramda/iterable/cons.py
pyramda/iterable/cons_test.py
pyramda/iterable/contains.py
pyramda/iterable/contains_test.py
pyramda/iterable/contains_with.py
pyramda/iterable/contains_with_test.py
pyramda/iterable/drop.py
pyramda/iterable/drop_test.py
pyramda/iterable/filter.py
pyramda/iterable/filter_test.py
pyramda/iterable/find.py
pyramda/iterable/find_test.py
pyramda/iterable/map.py
pyramda/iterable/map_test.py
pyramda/iterable/reduce.py
pyramda/iterable/reduce_test.py
pyramda/iterable/take.py
pyramda/iterable/take_test.py
pyramda/logic/__init__.py
pyramda/logic/all_pass.py
pyramda/logic/all_pass_test.py
pyramda/logic/and_func.py
pyramda/logic/and_func_test.py
pyramda/logic/any_pass.py
pyramda/logic/any_pass_test.py
pyramda/logic/both.py
pyramda/logic/both_test.py
