Metadata-Version: 1.0
Name: pyramda
Version: 0.1
Summary: A Python package for curried functional programming
Home-page: http://github.com/jackfirth/pyramda
Author: Jack Firth
Author-email: jackhfirth@gmail.com
License: UNKNOWN
Platform: UNKNOWN
